<annotation>
  <folder>VOC2007</folder>
  <filename>1039_0_ViwZgQfnrUBMFcO.jpg</filename>
  <source>
    <database>Coco database</database>
  </source>
  <size>
    <width>800</width>
    <height>600</height>
    <depth>3</depth>
  </size>
  <segmented>0</segmented>
  <object>
    <name>pothole</name>
    <pose>Unspecified</pose>
    <truncated>0</truncated>
    <difficult>0</difficult>
    <bndbox>
      <xmin>618</xmin>
      <ymin>264</ymin>
      <xmax>642</xmax>
      <ymax>277</ymax>
    </bndbox>
  </object>
  <object>
    <name>pothole</name>
    <pose>Unspecified</pose>
    <truncated>0</truncated>
    <difficult>0</difficult>
    <bndbox>
      <xmin>700</xmin>
      <ymin>250</ymin>
      <xmax>746</xmax>
      <ymax>266</ymax>
    </bndbox>
  </object>
  <object>
    <name>pothole</name>
    <pose>Unspecified</pose>
    <truncated>0</truncated>
    <difficult>0</difficult>
    <bndbox>
      <xmin>612</xmin>
      <ymin>237</ymin>
      <xmax>668</xmax>
      <ymax>250</ymax>
    </bndbox>
  </object>
  <object>
    <name>pothole</name>
    <pose>Unspecified</pose>
    <truncated>0</truncated>
    <difficult>0</difficult>
    <bndbox>
      <xmin>689</xmin>
      <ymin>208</ymin>
      <xmax>720</xmax>
      <ymax>227</ymax>
    </bndbox>
  </object>
</annotation>
