<annotation>
  <folder>VOC2007</folder>
  <filename>112_2_img-186_jpg.rf.c354a07266904a6e8212056359600aec.jpg</filename>
  <source>
    <database>Coco database</database>
  </source>
  <size>
    <width>720</width>
    <height>720</height>
    <depth>3</depth>
  </size>
  <segmented>0</segmented>
  <object>
    <name>pothole</name>
    <pose>Unspecified</pose>
    <truncated>0</truncated>
    <difficult>0</difficult>
    <bndbox>
      <xmin>307</xmin>
      <ymin>267</ymin>
      <xmax>598</xmax>
      <ymax>405</ymax>
    </bndbox>
  </object>
  <object>
    <name>pothole</name>
    <pose>Unspecified</pose>
    <truncated>0</truncated>
    <difficult>0</difficult>
    <bndbox>
      <xmin>36</xmin>
      <ymin>334</ymin>
      <xmax>280</xmax>
      <ymax>457</ymax>
    </bndbox>
  </object>
</annotation>
