<annotation>
  <folder>VOC2007</folder>
  <filename>1194_2_img-390_jpg.rf.3eeb4356ab769c112edf7f482110f8ee.jpg</filename>
  <source>
    <database>Coco database</database>
  </source>
  <size>
    <width>300</width>
    <height>400</height>
    <depth>3</depth>
  </size>
  <segmented>0</segmented>
  <object>
    <name>pothole</name>
    <pose>Unspecified</pose>
    <truncated>0</truncated>
    <difficult>0</difficult>
    <bndbox>
      <xmin>53</xmin>
      <ymin>71</ymin>
      <xmax>241</xmax>
      <ymax>370</ymax>
    </bndbox>
  </object>
</annotation>
