<annotation>
  <folder>VOC2007</folder>
  <filename>1222_1_img-526_jpg.rf.cfd028e96dd550e97745603cab99f3fe.jpg</filename>
  <source>
    <database>Coco database</database>
  </source>
  <size>
    <width>407</width>
    <height>300</height>
    <depth>3</depth>
  </size>
  <segmented>0</segmented>
  <object>
    <name>pothole</name>
    <pose>Unspecified</pose>
    <truncated>0</truncated>
    <difficult>0</difficult>
    <bndbox>
      <xmin>183</xmin>
      <ymin>150</ymin>
      <xmax>302</xmax>
      <ymax>183</ymax>
    </bndbox>
  </object>
  <object>
    <name>pothole</name>
    <pose>Unspecified</pose>
    <truncated>0</truncated>
    <difficult>0</difficult>
    <bndbox>
      <xmin>255</xmin>
      <ymin>120</ymin>
      <xmax>314</xmax>
      <ymax>151</ymax>
    </bndbox>
  </object>
  <object>
    <name>pothole</name>
    <pose>Unspecified</pose>
    <truncated>0</truncated>
    <difficult>0</difficult>
    <bndbox>
      <xmin>329</xmin>
      <ymin>144</ymin>
      <xmax>370</xmax>
      <ymax>157</ymax>
    </bndbox>
  </object>
  <object>
    <name>pothole</name>
    <pose>Unspecified</pose>
    <truncated>0</truncated>
    <difficult>0</difficult>
    <bndbox>
      <xmin>267</xmin>
      <ymin>167</ymin>
      <xmax>374</xmax>
      <ymax>218</ymax>
    </bndbox>
  </object>
  <object>
    <name>pothole</name>
    <pose>Unspecified</pose>
    <truncated>0</truncated>
    <difficult>0</difficult>
    <bndbox>
      <xmin>135</xmin>
      <ymin>218</ymin>
      <xmax>333</xmax>
      <ymax>254</ymax>
    </bndbox>
  </object>
  <object>
    <name>pothole</name>
    <pose>Unspecified</pose>
    <truncated>0</truncated>
    <difficult>0</difficult>
    <bndbox>
      <xmin>0</xmin>
      <ymin>178</ymin>
      <xmax>160</xmax>
      <ymax>252</ymax>
    </bndbox>
  </object>
  <object>
    <name>pothole</name>
    <pose>Unspecified</pose>
    <truncated>0</truncated>
    <difficult>0</difficult>
    <bndbox>
      <xmin>41</xmin>
      <ymin>266</ymin>
      <xmax>82</xmax>
      <ymax>299</ymax>
    </bndbox>
  </object>
  <object>
    <name>pothole</name>
    <pose>Unspecified</pose>
    <truncated>0</truncated>
    <difficult>0</difficult>
    <bndbox>
      <xmin>6</xmin>
      <ymin>142</ymin>
      <xmax>52</xmax>
      <ymax>153</ymax>
    </bndbox>
  </object>
  <object>
    <name>pothole</name>
    <pose>Unspecified</pose>
    <truncated>0</truncated>
    <difficult>0</difficult>
    <bndbox>
      <xmin>34</xmin>
      <ymin>152</ymin>
      <xmax>107</xmax>
      <ymax>187</ymax>
    </bndbox>
  </object>
  <object>
    <name>pothole</name>
    <pose>Unspecified</pose>
    <truncated>0</truncated>
    <difficult>0</difficult>
    <bndbox>
      <xmin>61</xmin>
      <ymin>138</ymin>
      <xmax>151</xmax>
      <ymax>154</ymax>
    </bndbox>
  </object>
</annotation>
