<annotation>
  <folder>VOC2007</folder>
  <filename>1246_1_left000299 - Copy.jpg</filename>
  <source>
    <database>Coco database</database>
  </source>
  <size>
    <width>1280</width>
    <height>720</height>
    <depth>3</depth>
  </size>
  <segmented>0</segmented>
  <object>
    <name>drain</name>
    <pose>Unspecified</pose>
    <truncated>0</truncated>
    <difficult>0</difficult>
    <bndbox>
      <xmin>422</xmin>
      <ymin>685</ymin>
      <xmax>582</xmax>
      <ymax>718</ymax>
    </bndbox>
  </object>
  <object>
    <name>drain</name>
    <pose>Unspecified</pose>
    <truncated>0</truncated>
    <difficult>0</difficult>
    <bndbox>
      <xmin>716</xmin>
      <ymin>649</ymin>
      <xmax>920</xmax>
      <ymax>718</ymax>
    </bndbox>
  </object>
</annotation>
