<annotation>
  <folder>VOC2007</folder>
  <filename>18_1_left000145.jpg</filename>
  <source>
    <database>Coco database</database>
  </source>
  <size>
    <width>1280</width>
    <height>720</height>
    <depth>3</depth>
  </size>
  <segmented>0</segmented>
  <object>
    <name>pothole</name>
    <pose>Unspecified</pose>
    <truncated>0</truncated>
    <difficult>0</difficult>
    <bndbox>
      <xmin>689</xmin>
      <ymin>513</ymin>
      <xmax>758</xmax>
      <ymax>527</ymax>
    </bndbox>
  </object>
  <object>
    <name>pothole</name>
    <pose>Unspecified</pose>
    <truncated>0</truncated>
    <difficult>0</difficult>
    <bndbox>
      <xmin>549</xmin>
      <ymin>502</ymin>
      <xmax>677</xmax>
      <ymax>524</ymax>
    </bndbox>
  </object>
</annotation>
