<annotation>
  <folder>VOC2007</folder>
  <filename>214_0_left000043 - Copy.jpg</filename>
  <source>
    <database>Coco database</database>
  </source>
  <size>
    <width>1280</width>
    <height>720</height>
    <depth>3</depth>
  </size>
  <segmented>0</segmented>
  <object>
    <name>drain</name>
    <pose>Unspecified</pose>
    <truncated>0</truncated>
    <difficult>0</difficult>
    <bndbox>
      <xmin>446</xmin>
      <ymin>271</ymin>
      <xmax>545</xmax>
      <ymax>321</ymax>
    </bndbox>
  </object>
  <object>
    <name>drain</name>
    <pose>Unspecified</pose>
    <truncated>0</truncated>
    <difficult>0</difficult>
    <bndbox>
      <xmin>593</xmin>
      <ymin>274</ymin>
      <xmax>686</xmax>
      <ymax>332</ymax>
    </bndbox>
  </object>
</annotation>
