<annotation>
  <folder>VOC2007</folder>
  <filename>24_3_img-158_jpg.rf.80110529bda206547f2c5482abfca272.jpg</filename>
  <source>
    <database>Coco database</database>
  </source>
  <size>
    <width>720</width>
    <height>720</height>
    <depth>3</depth>
  </size>
  <segmented>0</segmented>
  <object>
    <name>pothole</name>
    <pose>Unspecified</pose>
    <truncated>0</truncated>
    <difficult>0</difficult>
    <bndbox>
      <xmin>311</xmin>
      <ymin>296</ymin>
      <xmax>429</xmax>
      <ymax>462</ymax>
    </bndbox>
  </object>
  <object>
    <name>pothole</name>
    <pose>Unspecified</pose>
    <truncated>0</truncated>
    <difficult>0</difficult>
    <bndbox>
      <xmin>299</xmin>
      <ymin>157</ymin>
      <xmax>385</xmax>
      <ymax>293</ymax>
    </bndbox>
  </object>
</annotation>
