<annotation>
  <folder>VOC2007</folder>
  <filename>416_2_left000249 - Copy.jpg</filename>
  <source>
    <database>Coco database</database>
  </source>
  <size>
    <width>1280</width>
    <height>720</height>
    <depth>3</depth>
  </size>
  <segmented>0</segmented>
  <object>
    <name>drain</name>
    <pose>Unspecified</pose>
    <truncated>0</truncated>
    <difficult>0</difficult>
    <bndbox>
      <xmin>551</xmin>
      <ymin>297</ymin>
      <xmax>636</xmax>
      <ymax>337</ymax>
    </bndbox>
  </object>
  <object>
    <name>drain</name>
    <pose>Unspecified</pose>
    <truncated>0</truncated>
    <difficult>0</difficult>
    <bndbox>
      <xmin>685</xmin>
      <ymin>296</ymin>
      <xmax>777</xmax>
      <ymax>345</ymax>
    </bndbox>
  </object>
</annotation>
