<annotation>
  <folder>VOC2007</folder>
  <filename>418_6_img-89_jpg.rf.4cc9eb15fe4de48faa685770d8299408.jpg</filename>
  <source>
    <database>Coco database</database>
  </source>
  <size>
    <width>720</width>
    <height>720</height>
    <depth>3</depth>
  </size>
  <segmented>0</segmented>
  <object>
    <name>pothole</name>
    <pose>Unspecified</pose>
    <truncated>0</truncated>
    <difficult>0</difficult>
    <bndbox>
      <xmin>227</xmin>
      <ymin>248</ymin>
      <xmax>437</xmax>
      <ymax>386</ymax>
    </bndbox>
  </object>
  <object>
    <name>pothole</name>
    <pose>Unspecified</pose>
    <truncated>0</truncated>
    <difficult>0</difficult>
    <bndbox>
      <xmin>571</xmin>
      <ymin>465</ymin>
      <xmax>646</xmax>
      <ymax>549</ymax>
    </bndbox>
  </object>
</annotation>
