<annotation>
  <folder>VOC2007</folder>
  <filename>571_3_img-440_jpg.rf.4475e2f277c4b84b9d5ae3095916bffa.jpg</filename>
  <source>
    <database>Coco database</database>
  </source>
  <size>
    <width>300</width>
    <height>533</height>
    <depth>3</depth>
  </size>
  <segmented>0</segmented>
  <object>
    <name>pothole</name>
    <pose>Unspecified</pose>
    <truncated>0</truncated>
    <difficult>0</difficult>
    <bndbox>
      <xmin>2</xmin>
      <ymin>92</ymin>
      <xmax>262</xmax>
      <ymax>516</ymax>
    </bndbox>
  </object>
</annotation>
