<annotation>
  <folder>VOC2007</folder>
  <filename>678_1_img-32_jpg.rf.3889f9f6223819080bb08c1149fb64d1.jpg</filename>
  <source>
    <database>Coco database</database>
  </source>
  <size>
    <width>720</width>
    <height>720</height>
    <depth>3</depth>
  </size>
  <segmented>0</segmented>
  <object>
    <name>pothole</name>
    <pose>Unspecified</pose>
    <truncated>0</truncated>
    <difficult>0</difficult>
    <bndbox>
      <xmin>467</xmin>
      <ymin>146</ymin>
      <xmax>611</xmax>
      <ymax>234</ymax>
    </bndbox>
  </object>
  <object>
    <name>pothole</name>
    <pose>Unspecified</pose>
    <truncated>0</truncated>
    <difficult>0</difficult>
    <bndbox>
      <xmin>215</xmin>
      <ymin>277</ymin>
      <xmax>467</xmax>
      <ymax>501</ymax>
    </bndbox>
  </object>
</annotation>
