<annotation>
  <folder>VOC2007</folder>
  <filename>782_0_left000286 - Copy.jpg</filename>
  <source>
    <database>Coco database</database>
  </source>
  <size>
    <width>1280</width>
    <height>720</height>
    <depth>3</depth>
  </size>
  <segmented>0</segmented>
  <object>
    <name>drain</name>
    <pose>Unspecified</pose>
    <truncated>0</truncated>
    <difficult>0</difficult>
    <bndbox>
      <xmin>639</xmin>
      <ymin>141</ymin>
      <xmax>740</xmax>
      <ymax>182</ymax>
    </bndbox>
  </object>
  <object>
    <name>drain</name>
    <pose>Unspecified</pose>
    <truncated>0</truncated>
    <difficult>0</difficult>
    <bndbox>
      <xmin>454</xmin>
      <ymin>116</ymin>
      <xmax>576</xmax>
      <ymax>183</ymax>
    </bndbox>
  </object>
</annotation>
