<annotation>
  <folder>VOC2007</folder>
  <filename>810_2_left000085.jpg</filename>
  <source>
    <database>Coco database</database>
  </source>
  <size>
    <width>1280</width>
    <height>720</height>
    <depth>3</depth>
  </size>
  <segmented>0</segmented>
  <object>
    <name>pothole</name>
    <pose>Unspecified</pose>
    <truncated>0</truncated>
    <difficult>0</difficult>
    <bndbox>
      <xmin>672</xmin>
      <ymin>143</ymin>
      <xmax>740</xmax>
      <ymax>157</ymax>
    </bndbox>
  </object>
  <object>
    <name>pothole</name>
    <pose>Unspecified</pose>
    <truncated>0</truncated>
    <difficult>0</difficult>
    <bndbox>
      <xmin>554</xmin>
      <ymin>145</ymin>
      <xmax>667</xmax>
      <ymax>165</ymax>
    </bndbox>
  </object>
</annotation>
