<annotation>
  <folder>VOC2007</folder>
  <filename>812_3_p42.jpg</filename>
  <source>
    <database>Coco database</database>
  </source>
  <size>
    <width>160</width>
    <height>240</height>
    <depth>3</depth>
  </size>
  <segmented>0</segmented>
  <object>
    <name>pothole</name>
    <pose>Unspecified</pose>
    <truncated>0</truncated>
    <difficult>0</difficult>
    <bndbox>
      <xmin>72</xmin>
      <ymin>0</ymin>
      <xmax>119</xmax>
      <ymax>212</ymax>
    </bndbox>
  </object>
  <object>
    <name>pothole</name>
    <pose>Unspecified</pose>
    <truncated>0</truncated>
    <difficult>0</difficult>
    <bndbox>
      <xmin>37</xmin>
      <ymin>0</ymin>
      <xmax>73</xmax>
      <ymax>170</ymax>
    </bndbox>
  </object>
  <object>
    <name>pothole</name>
    <pose>Unspecified</pose>
    <truncated>0</truncated>
    <difficult>0</difficult>
    <bndbox>
      <xmin>1</xmin>
      <ymin>0</ymin>
      <xmax>39</xmax>
      <ymax>148</ymax>
    </bndbox>
  </object>
</annotation>
