<annotation>
  <folder>VOC2007</folder>
  <filename>851_0_img-621_jpg.rf.9721804149e82d9ebc58f8d19a01d044.jpg</filename>
  <source>
    <database>Coco database</database>
  </source>
  <size>
    <width>303</width>
    <height>300</height>
    <depth>3</depth>
  </size>
  <segmented>0</segmented>
  <object>
    <name>pothole</name>
    <pose>Unspecified</pose>
    <truncated>0</truncated>
    <difficult>0</difficult>
    <bndbox>
      <xmin>196</xmin>
      <ymin>117</ymin>
      <xmax>239</xmax>
      <ymax>155</ymax>
    </bndbox>
  </object>
  <object>
    <name>pothole</name>
    <pose>Unspecified</pose>
    <truncated>0</truncated>
    <difficult>0</difficult>
    <bndbox>
      <xmin>6</xmin>
      <ymin>182</ymin>
      <xmax>114</xmax>
      <ymax>257</ymax>
    </bndbox>
  </object>
  <object>
    <name>pothole</name>
    <pose>Unspecified</pose>
    <truncated>0</truncated>
    <difficult>0</difficult>
    <bndbox>
      <xmin>0</xmin>
      <ymin>260</ymin>
      <xmax>48</xmax>
      <ymax>276</ymax>
    </bndbox>
  </object>
  <object>
    <name>pothole</name>
    <pose>Unspecified</pose>
    <truncated>0</truncated>
    <difficult>0</difficult>
    <bndbox>
      <xmin>146</xmin>
      <ymin>230</ymin>
      <xmax>214</xmax>
      <ymax>255</ymax>
    </bndbox>
  </object>
  <object>
    <name>pothole</name>
    <pose>Unspecified</pose>
    <truncated>0</truncated>
    <difficult>0</difficult>
    <bndbox>
      <xmin>223</xmin>
      <ymin>212</ymin>
      <xmax>287</xmax>
      <ymax>235</ymax>
    </bndbox>
  </object>
  <object>
    <name>pothole</name>
    <pose>Unspecified</pose>
    <truncated>0</truncated>
    <difficult>0</difficult>
    <bndbox>
      <xmin>0</xmin>
      <ymin>79</ymin>
      <xmax>43</xmax>
      <ymax>143</ymax>
    </bndbox>
  </object>
</annotation>
