<annotation>
  <folder>VOC2007</folder>
  <filename>866_3_left000945.jpg</filename>
  <source>
    <database>Coco database</database>
  </source>
  <size>
    <width>720</width>
    <height>1280</height>
    <depth>3</depth>
  </size>
  <segmented>0</segmented>
  <object>
    <name>pothole</name>
    <pose>Unspecified</pose>
    <truncated>0</truncated>
    <difficult>0</difficult>
    <bndbox>
      <xmin>278</xmin>
      <ymin>748</ymin>
      <xmax>308</xmax>
      <ymax>825</ymax>
    </bndbox>
  </object>
  <object>
    <name>pothole</name>
    <pose>Unspecified</pose>
    <truncated>0</truncated>
    <difficult>0</difficult>
    <bndbox>
      <xmin>211</xmin>
      <ymin>499</ymin>
      <xmax>270</xmax>
      <ymax>776</ymax>
    </bndbox>
  </object>
</annotation>
