<annotation>
  <folder>VOC2007</folder>
  <filename>880_7_aAAwuvUBxwBSvhR.jpg</filename>
  <source>
    <database>Coco database</database>
  </source>
  <size>
    <width>800</width>
    <height>600</height>
    <depth>3</depth>
  </size>
  <segmented>0</segmented>
  <object>
    <name>pothole</name>
    <pose>Unspecified</pose>
    <truncated>0</truncated>
    <difficult>0</difficult>
    <bndbox>
      <xmin>278</xmin>
      <ymin>284</ymin>
      <xmax>322</xmax>
      <ymax>300</ymax>
    </bndbox>
  </object>
</annotation>
