<annotation>
  <folder>VOC2007</folder>
  <filename>914_2_img-619_jpg.rf.5456a9e84bd2369e8f206f5c19410127.jpg</filename>
  <source>
    <database>Coco database</database>
  </source>
  <size>
    <width>472</width>
    <height>300</height>
    <depth>3</depth>
  </size>
  <segmented>0</segmented>
  <object>
    <name>pothole</name>
    <pose>Unspecified</pose>
    <truncated>0</truncated>
    <difficult>0</difficult>
    <bndbox>
      <xmin>125</xmin>
      <ymin>110</ymin>
      <xmax>315</xmax>
      <ymax>193</ymax>
    </bndbox>
  </object>
</annotation>
